{
	"version":"0.1",
	"id":"00f0cf0c049bffcf007fc3d69f65a13a",
	"updated":"1970-01-01 00:00:00",
	"vtypes":
	[
		"motorcycle",
		"passenger-car",
		"light-truck-van",
		"bus",
		"two-axle-six-tire-single-unit-truck",
		"three-axle-single-unit-truck",
		"four-or-more-axle-single-unit-truck",
		"four-or-fewer-axle-single-trailer-truck",
		"five-axle-single-trailer-truck",
		"six-or-more-axle-single-trailer-truck",
		"five-or-fewer-axle-multi-trailer-truck",
		"six-axle-multi-trailer-truck",
		"seven-or-more-axle-multi-trailer-truck"
	],
	"schedule":
	{
		"start":"1970-01-01 00:00:00",
		"end":"292278994-08-17 07:12:55",
		"dow":"SMTWRFA"
	},
	"regulatory":true,
	"controltype":"direction",
	"controlvalue":"1",
	"proj":"epsg:3785",
	"datum":"WGS84",
	"label":"",
	"time":"1970-01-01 00:00:00",
	"lon":681,
	"lat":20102,
	"alt":0,
	"heading":2681,
	"points":
	[
		{"x":0, "y":0},
		{"x":18, "y":556},
		{"x":37, "y":550},
		{"x":58, "y":553},
		{"x":77, "y":545},
		{"x":98, "y":548},
		{"x":116, "y":538},
		{"x":136, "y":540},
		{"x":155, "y":528},
		{"x":175, "y":528},
		{"x":192, "y":516},
		{"x":213, "y":513},
		{"x":229, "y":501},
		{"x":77, "y":155},
		{"x":77, "y":156}
	]
}
